<templateSet group="heflat">
  <template name="hnotBlank" value="if (StringUtils.isNotBlank($args$)) {&#10;    $END$&#10;}" description="StringUtils.isNotBlank()" toReformat="false" toShortenFQNames="true">
    <variable name="args" expression="" defaultValue="" alwaysStopAt="true" />
    <context>
      <option name="JAVA_CODE" value="true" />
    </context>
  </template>
  <template name="hblank" value="if (StringUtils.isBlank($args$)) {&#10;    $END$&#10;}" description="StringUtils.isBlank()" toReformat="false" toShortenFQNames="true">
    <variable name="args" expression="" defaultValue="" alwaysStopAt="true" />
    <context>
      <option name="JAVA_CODE" value="true" />
    </context>
  </template>
  <template name="hnotEmpty" value="if (CollectionUtils.isNotEmpty($args$)) {&#10;    $END$&#10;}" description="CollectionUtils.isNotEmpty();" toReformat="false" toShortenFQNames="true">
    <variable name="args" expression="" defaultValue="" alwaysStopAt="true" />
    <context>
      <option name="JAVA_CODE" value="true" />
    </context>
  </template>
  <template name="hempty" value="if (CollectionUtils.isEmpty($args$)) {&#10;    $END$&#10;}" description="CollectionUtils.isEmpty()" toReformat="false" toShortenFQNames="true">
    <variable name="args" expression="" defaultValue="" alwaysStopAt="true" />
    <context>
      <option name="JAVA_CODE" value="true" />
    </context>
  </template>
  <template name="pInteger" value="/** $desc$ */&#10;private Integer $field$;$END$" description="private Integer field;" toReformat="false" toShortenFQNames="true">
    <variable name="field" expression="" defaultValue="" alwaysStopAt="true" />
    <variable name="desc" expression="" defaultValue="" alwaysStopAt="true" />
    <context>
      <option name="JAVA_CODE" value="true" />
    </context>
  </template>
  <template name="pint" value="/** $desc$ */&#10;private int $field$;$END$" description="private int field;" toReformat="false" toShortenFQNames="true">
    <variable name="field" expression="" defaultValue="" alwaysStopAt="true" />
    <variable name="desc" expression="" defaultValue="" alwaysStopAt="true" />
    <context>
      <option name="JAVA_CODE" value="true" />
    </context>
  </template>
  <template name="pString" value="/** $desc$ */&#10;private String $field$;$END$" description="private String field;" toReformat="false" toShortenFQNames="true">
    <variable name="field" expression="" defaultValue="" alwaysStopAt="true" />
    <variable name="desc" expression="" defaultValue="" alwaysStopAt="true" />
    <context>
      <option name="JAVA_CODE" value="true" />
    </context>
  </template>
  <template name="pFloat" value="/** $desc$ */&#10;private Float $field$;$END$" description="private Float field;" toReformat="false" toShortenFQNames="true">
    <variable name="field" expression="" defaultValue="" alwaysStopAt="true" />
    <variable name="desc" expression="" defaultValue="" alwaysStopAt="true" />
    <context>
      <option name="JAVA_CODE" value="true" />
    </context>
  </template>
  <template name="pDouble" value="/** $desc$ */&#10;private Double $field$;$END$" description="private Double field;" toReformat="false" toShortenFQNames="true">
    <variable name="field" expression="" defaultValue="" alwaysStopAt="true" />
    <variable name="desc" expression="" defaultValue="" alwaysStopAt="true" />
    <context>
      <option name="JAVA_CODE" value="true" />
    </context>
  </template>
  <template name="pdouble" value="/** $desc$ */&#10;private double $field$;$END$" description="private double field;" toReformat="false" toShortenFQNames="true">
    <variable name="field" expression="" defaultValue="" alwaysStopAt="true" />
    <variable name="desc" expression="" defaultValue="" alwaysStopAt="true" />
    <context>
      <option name="JAVA_CODE" value="true" />
    </context>
  </template>
  <template name="newArrayList" value="List&lt;$obj$&gt; $name$ = new ArrayList&lt;&gt;();" description="List&lt;Object&gt; list = new ArrayList&lt;&gt;();" toReformat="false" toShortenFQNames="true">
    <variable name="obj" expression="" defaultValue="" alwaysStopAt="true" />
    <variable name="name" expression="" defaultValue="" alwaysStopAt="true" />
    <context>
      <option name="JAVA_CODE" value="true" />
    </context>
  </template>
  <template name="newHashMap" value="Map&lt;$key$, $value$&gt; $name$ = new HashMap&lt;&gt;();" description="Map&lt;Object, Object&gt; map = new HashedMap();" toReformat="false" toShortenFQNames="true">
    <variable name="key" expression="" defaultValue="" alwaysStopAt="true" />
    <variable name="value" expression="" defaultValue="" alwaysStopAt="true" />
    <variable name="name" expression="" defaultValue="" alwaysStopAt="true" />
    <context>
      <option name="JAVA_CODE" value="true" />
    </context>
  </template>
  <template name="newHashSet" value="Set&lt;$obj$&gt; $name$ = new HashSet&lt;&gt;();" description="Set&lt;Object&gt; $name$ = new HashSet&lt;&gt;()" toReformat="false" toShortenFQNames="true">
    <variable name="obj" expression="" defaultValue="" alwaysStopAt="true" />
    <variable name="name" expression="" defaultValue="" alwaysStopAt="true" />
    <context>
      <option name="JAVA_CODE" value="true" />
    </context>
  </template>
  <template name="newLinkedList" value="List&lt;$obj$&gt; $name$ = new LinkedList&lt;&gt;();" description="List&lt;Object&gt; list = new LinkedList&lt;&gt;();" toReformat="false" toShortenFQNames="true">
    <variable name="obj" expression="" defaultValue="" alwaysStopAt="true" />
    <variable name="name" expression="" defaultValue="" alwaysStopAt="true" />
    <context>
      <option name="JAVA_CODE" value="true" />
    </context>
  </template>
  <template name="pBigDecimal" value="/** $desc$ */&#10;private BigDecimal $field$;$END$" description="private BigDecimal field;" toReformat="false" toShortenFQNames="true">
    <variable name="field" expression="" defaultValue="" alwaysStopAt="true" />
    <variable name="desc" expression="" defaultValue="" alwaysStopAt="true" />
    <context>
      <option name="JAVA_CODE" value="true" />
    </context>
  </template>
  <template name="hnotNull" value="if ($arg$ != null) {&#10;    $END$&#10;}" description="if (arg != null) {}" toReformat="false" toShortenFQNames="true">
    <variable name="arg" expression="" defaultValue="" alwaysStopAt="true" />
    <context>
      <option name="JAVA_CODE" value="true" />
    </context>
  </template>
  <template name="hnull" value="if ($arg$ == null) {&#10;    $END$&#10;}" description="if (arg == null) {}" toReformat="false" toShortenFQNames="true">
    <variable name="arg" expression="" defaultValue="" alwaysStopAt="true" />
    <context>
      <option name="JAVA_CODE" value="true" />
    </context>
  </template>
  <template name="main" value="public static void main(String[] args) {&#10;    $END$&#10;}" description="main()" toReformat="false" toShortenFQNames="true">
    <context>
      <option name="JAVA_CODE" value="true" />
    </context>
  </template>
  <template name="pfloat" value="/** $desc$ */&#10;private float $field$;$END$" description="private float field;" toReformat="false" toShortenFQNames="true">
    <variable name="desc" expression="" defaultValue="" alwaysStopAt="true" />
    <variable name="field" expression="" defaultValue="" alwaysStopAt="true" />
    <context>
      <option name="JAVA_CODE" value="true" />
    </context>
  </template>
  <template name="hsplit" value="StringUtils.split($str$, $separatorChars$)" description="StringUtils.split($str$, $separatorChars$)" toReformat="false" toShortenFQNames="true">
    <variable name="str" expression="" defaultValue="" alwaysStopAt="true" />
    <variable name="separatorChars" expression="" defaultValue="" alwaysStopAt="true" />
    <context>
      <option name="JAVA_CODE" value="true" />
    </context>
  </template>
  <template name="hjoin" value="StringUtils.join($collection$, $separatorChars$)" description="StringUtils.join($collection$, $separatorChars$)" toReformat="false" toShortenFQNames="true">
    <variable name="collection" expression="" defaultValue="" alwaysStopAt="true" />
    <variable name="separatorChars" expression="" defaultValue="" alwaysStopAt="true" />
    <context>
      <option name="JAVA_CODE" value="true" />
    </context>
  </template>
  <template name="hequals" value="StringUtils.equals($str1$, $str2$)" description="StringUtils.equals($str1$, $str2$)" toReformat="false" toShortenFQNames="true">
    <variable name="str1" expression="" defaultValue="" alwaysStopAt="true" />
    <variable name="str2" expression="" defaultValue="" alwaysStopAt="true" />
    <context>
      <option name="JAVA_CODE" value="true" />
    </context>
  </template>
  <template name="hequalsIgnoreCase" value="StringUtils.equalsIgnoreCase($str1$, $str2$)" description="StringUtils.equalsIgnoreCase($str1$, $str2$)" toReformat="false" toShortenFQNames="true">
    <variable name="str1" expression="" defaultValue="" alwaysStopAt="true" />
    <variable name="str2" expression="" defaultValue="" alwaysStopAt="true" />
    <context>
      <option name="JAVA_CODE" value="true" />
    </context>
  </template>
  <template name="htrim" value="StringUtils.trim($str$)" description="StringUtils.trim($str$)" toReformat="false" toShortenFQNames="true">
    <variable name="str" expression="" defaultValue="" alwaysStopAt="true" />
    <context>
      <option name="JAVA_CODE" value="true" />
    </context>
  </template>
  <template name="hept" value="StringUtils.EMPTY" description="StringUtils.EMPTY" toReformat="false" toShortenFQNames="true">
    <context>
      <option name="JAVA_CODE" value="true" />
    </context>
  </template>
  <template name="pDate" value="/** $desc$ */&#10;private Date $field$;$END$" description="private Date field;" toReformat="false" toShortenFQNames="true">
    <variable name="field" expression="" defaultValue="" alwaysStopAt="true" />
    <variable name="desc" expression="" defaultValue="" alwaysStopAt="true" />
    <context>
      <option name="JAVA_CODE" value="true" />
    </context>
  </template>
  <template name="cdesc" value="/**&#10; * $desc$&#10; * &#10; * @author heflat&#10; * @date $date$&#10; */" description="add a doc description" toReformat="false" toShortenFQNames="true">
    <variable name="desc" expression="" defaultValue="" alwaysStopAt="true" />
    <variable name="date" expression="date(&quot;yyyy-MM-dd HH:mm&quot;)" defaultValue="" alwaysStopAt="false" />
    <context>
      <option name="JAVA_CODE" value="true" />
    </context>
  </template>
</templateSet>